diptorch/__init__.py
diptorch/_modidx.py
diptorch/filters.py
diptorch/linalg.py
diptorch/utils.py
diptorch-0.0.1.dist-info/LICENSE
diptorch-0.0.1.dist-info/METADATA
diptorch-0.0.1.dist-info/WHEEL
diptorch-0.0.1.dist-info/entry_points.txt
diptorch-0.0.1.dist-info/top_level.txt
diptorch-0.0.1.dist-info/RECORD
