Metadata-Version: 2.1
Name: diptorch
Version: 0.0.1
Summary: Digital image processing in PyTorch
Home-page: https://github.com/eigenvivek/diptorch
Author: Vivek Gopalakrishnan
Author-email: vivekg@mit.edu
License: MIT License
Keywords: nbdev jupyter notebook python
Classifier: Development Status :: 4 - Beta
Classifier: Intended Audience :: Developers
Classifier: Natural Language :: English
Classifier: Programming Language :: Python :: 3.7
Classifier: Programming Language :: Python :: 3.8
Classifier: Programming Language :: Python :: 3.9
Classifier: Programming Language :: Python :: 3.10
Classifier: License :: OSI Approved :: MIT License
Requires-Python: >=3.7
License-File: LICENSE
Requires-Dist: einops
Requires-Dist: matplotlib
Requires-Dist: scikit-image
Requires-Dist: torch
Provides-Extra: dev
Requires-Dist: nbdev ; extra == 'dev'
Requires-Dist: black ; extra == 'dev'
Requires-Dist: flake8 ; extra == 'dev'
Requires-Dist: ipykernel ; extra == 'dev'
Requires-Dist: ipywidgets ; extra == 'dev'
Requires-Dist: jupyterlab ; extra == 'dev'
Requires-Dist: jupyterlab-execute-time ; extra == 'dev'
Requires-Dist: jupyterlab-code-formatter ; extra == 'dev'
Requires-Dist: isort ; extra == 'dev'
